{
  "domain": "products",
  "description": "Product-related query examples",
  "tables": [
    "Product",
    "OrderItem",
    "ProductGroup",
    "ProductPricing"
  ],
  "examples": [
    {
      "id": "prod_count_001",
      "category": "aggregation",
      "complexity": "simple",
      "question_en": "How many products do we have?",
      "question_uk": "Скільки у нас товарів?",
      "variations_en": [
        "total number of products",
        "count all products",
        "product count"
      ],
      "variations_uk": [
        "загальна кількість товарів",
        "порахуй товари",
        "кількість продуктів"
      ],
      "sql": "SELECT COUNT(*) as TotalProducts FROM dbo.Product WHERE Deleted = 0",
      "tables_used": [
        "Product"
      ]
    },
    {
      "id": "prod_count_active_002",
      "category": "aggregation",
      "complexity": "simple",
      "question_en": "How many active products for sale?",
      "question_uk": "Скільки активних товарів на продаж?",
      "variations_en": [
        "products available for sale",
        "sellable products count"
      ],
      "variations_uk": [
        "товари доступні для продажу",
        "скільки можна продати"
      ],
      "sql": "SELECT COUNT(*) as ActiveProducts FROM dbo.Product WHERE Deleted = 0 AND IsForSale = 1",
      "tables_used": [
        "Product"
      ]
    },
    {
      "id": "prod_search_sem_003",
      "category": "search",
      "complexity": "simple",
      "question_en": "Find products with SEM in code",
      "question_uk": "Знайди товари з кодом SEM",
      "variations_en": [
        "products with SEM",
        "SEM products",
        "show SEM items",
        "show all SEM products",
        "list SEM products"
      ],
      "variations_uk": [
        "товари SEM",
        "покажи SEM",
        "продукти з SEM",
        "покажи всі товари SEM",
        "всі товари SEM",
        "список товарів SEM"
      ],
      "sql": "SELECT TOP 100 ID, Name, VendorCode FROM dbo.Product WHERE Deleted = 0 AND VendorCode LIKE N'SEM%' ORDER BY VendorCode",
      "tables_used": [
        "Product"
      ]
    },
    {
      "id": "prod_search_mg_004",
      "category": "search",
      "complexity": "simple",
      "question_en": "Find products with MG code",
      "question_uk": "Знайди товари з кодом MG",
      "variations_en": [
        "MG products",
        "show MG items",
        "products starting with MG"
      ],
      "variations_uk": [
        "товари MG",
        "покажи MG",
        "продукти MG"
      ],
      "sql": "SELECT TOP 50 ID, Name, VendorCode FROM dbo.Product WHERE Deleted = 0 AND (VendorCode LIKE 'MG%' OR Name LIKE '%MG%') ORDER BY VendorCode",
      "tables_used": [
        "Product"
      ]
    },
    {
      "id": "prod_top_sales_005",
      "category": "ranking",
      "complexity": "medium",
      "question_en": "Show top 10 products by sales quantity",
      "question_uk": "Покажи топ 10 товарів за кількістю продажів",
      "variations_en": [
        "best selling products",
        "most sold products",
        "top sellers",
        "products with highest sales"
      ],
      "variations_uk": [
        "найпопулярніші товари",
        "товари лідери продажів",
        "найкращі товари",
        "що найкраще продається"
      ],
      "sql": "SELECT TOP 10 p.ID, p.Name, p.VendorCode, SUM(oi.Qty) as TotalSold FROM dbo.Product p JOIN dbo.OrderItem oi ON p.ID = oi.ProductID WHERE p.Deleted = 0 AND oi.Deleted = 0 GROUP BY p.ID, p.Name, p.VendorCode ORDER BY TotalSold DESC",
      "tables_used": [
        "Product",
        "OrderItem"
      ]
    },
    {
      "id": "prod_top_orders_006",
      "category": "ranking",
      "complexity": "medium",
      "question_en": "Top 10 products by number of orders",
      "question_uk": "Топ 10 товарів за кількістю замовлень",
      "variations_en": [
        "most ordered products",
        "products with most orders",
        "frequently ordered"
      ],
      "variations_uk": [
        "товари з найбільшою кількістю замовлень",
        "часто замовляють",
        "популярні товари"
      ],
      "sql": "SELECT TOP 10 p.ID, p.Name, p.VendorCode, COUNT(DISTINCT oi.OrderID) as OrderCount FROM dbo.Product p JOIN dbo.OrderItem oi ON p.ID = oi.ProductID WHERE p.Deleted = 0 AND oi.Deleted = 0 GROUP BY p.ID, p.Name, p.VendorCode ORDER BY OrderCount DESC",
      "tables_used": [
        "Product",
        "OrderItem"
      ]
    },
    {
      "id": "prod_top_20_007",
      "category": "ranking",
      "complexity": "medium",
      "question_en": "Show top 20 best selling products",
      "question_uk": "Покажи топ 20 найкращих товарів",
      "variations_en": [
        "20 best sellers",
        "top twenty products"
      ],
      "variations_uk": [
        "двадцять найкращих",
        "20 лідерів"
      ],
      "sql": "SELECT TOP 20 p.ID, p.Name, p.VendorCode, SUM(oi.Qty) as TotalSold FROM dbo.Product p JOIN dbo.OrderItem oi ON p.ID = oi.ProductID WHERE p.Deleted = 0 AND oi.Deleted = 0 GROUP BY p.ID, p.Name, p.VendorCode ORDER BY TotalSold DESC",
      "tables_used": [
        "Product",
        "OrderItem"
      ]
    },
    {
      "id": "prod_zero_sales_008",
      "category": "filter",
      "complexity": "medium",
      "question_en": "Products with zero sales",
      "question_uk": "Товари без продажів",
      "variations_en": [
        "unsold products",
        "products never sold",
        "products with no sales"
      ],
      "variations_uk": [
        "непродані товари",
        "товари які не продавались",
        "нульові продажі"
      ],
      "sql": "SELECT TOP 100 p.ID, p.Name, p.VendorCode FROM dbo.Product p LEFT JOIN dbo.OrderItem oi ON p.ID = oi.ProductID AND oi.Deleted = 0 WHERE p.Deleted = 0 AND p.IsForSale = 1 AND oi.ID IS NULL ORDER BY p.Created DESC",
      "tables_used": [
        "Product",
        "OrderItem"
      ]
    },
    {
      "id": "prod_low_sales_009",
      "category": "filter",
      "complexity": "medium",
      "question_en": "Products with less than 10 sales",
      "question_uk": "Товари з продажами менше 10",
      "variations_en": [
        "low selling products",
        "products sold less than 10 times"
      ],
      "variations_uk": [
        "товари з низькими продажами",
        "мало продається"
      ],
      "sql": "SELECT p.ID, p.Name, p.VendorCode, COALESCE(SUM(oi.Qty), 0) as TotalSold FROM dbo.Product p LEFT JOIN dbo.OrderItem oi ON p.ID = oi.ProductID AND oi.Deleted = 0 WHERE p.Deleted = 0 AND p.IsForSale = 1 GROUP BY p.ID, p.Name, p.VendorCode HAVING COALESCE(SUM(oi.Qty), 0) < 10 ORDER BY TotalSold DESC",
      "tables_used": [
        "Product",
        "OrderItem"
      ]
    },
    {
      "id": "prod_compare_sem_mg_010",
      "category": "comparison",
      "complexity": "complex",
      "question_en": "Compare SEM and MG brand sales",
      "question_uk": "Порівняй продажі SEM та MG",
      "variations_en": [
        "SEM vs MG",
        "compare SEM with MG",
        "which sells better SEM or MG"
      ],
      "variations_uk": [
        "SEM проти MG",
        "порівняння SEM і MG",
        "що краще продається SEM чи MG"
      ],
      "sql": "SELECT CASE WHEN p.VendorCode LIKE 'SEM%' THEN 'SEM' WHEN p.VendorCode LIKE 'MG%' THEN 'MG' END as Brand, COUNT(DISTINCT p.ID) as ProductCount, SUM(oi.Qty) as TotalSold, COUNT(DISTINCT oi.OrderID) as OrderCount FROM dbo.Product p JOIN dbo.OrderItem oi ON p.ID = oi.ProductID WHERE p.Deleted = 0 AND oi.Deleted = 0 AND (p.VendorCode LIKE 'SEM%' OR p.VendorCode LIKE 'MG%') GROUP BY CASE WHEN p.VendorCode LIKE 'SEM%' THEN 'SEM' WHEN p.VendorCode LIKE 'MG%' THEN 'MG' END",
      "tables_used": [
        "Product",
        "OrderItem"
      ]
    },
    {
      "id": "prod_new_products_011",
      "category": "filter",
      "complexity": "simple",
      "question_en": "Products added this month",
      "question_uk": "Товари додані цього місяця",
      "variations_en": [
        "new products",
        "recently added products",
        "products this month"
      ],
      "variations_uk": [
        "нові товари",
        "недавно додані",
        "товари за місяць"
      ],
      "sql": "SELECT TOP 100 ID, Name, VendorCode, Created FROM dbo.Product WHERE Deleted = 0 AND MONTH(Created) = MONTH(GETDATE()) AND YEAR(Created) = YEAR(GETDATE()) ORDER BY Created DESC",
      "tables_used": [
        "Product"
      ]
    },
    {
      "id": "prod_new_year_012",
      "category": "filter",
      "complexity": "simple",
      "question_en": "Products added this year",
      "question_uk": "Товари додані цього року",
      "variations_en": [
        "products in 2024",
        "this year products",
        "new products 2024"
      ],
      "variations_uk": [
        "товари 2024",
        "нові товари за рік",
        "додані у 2024"
      ],
      "sql": "SELECT TOP 100 ID, Name, VendorCode, Created FROM dbo.Product WHERE Deleted = 0 AND YEAR(Created) = YEAR(GETDATE()) ORDER BY Created DESC",
      "tables_used": [
        "Product"
      ]
    },
    {
      "id": "prod_search_name_013",
      "category": "search",
      "complexity": "simple",
      "question_en": "Find products with word brake",
      "question_uk": "Знайди товари зі словом гальма",
      "variations_en": [
        "brake products",
        "search brake",
        "products containing brake"
      ],
      "variations_uk": [
        "товари гальма",
        "пошук гальма",
        "гальмівні товари"
      ],
      "sql": "SELECT TOP 50 ID, Name, VendorCode FROM dbo.Product WHERE Deleted = 0 AND (Name LIKE N'%гальм%' OR Name LIKE '%brake%') ORDER BY Name",
      "tables_used": [
        "Product"
      ]
    },
    {
      "id": "prod_for_web_014",
      "category": "filter",
      "complexity": "simple",
      "question_en": "Products available on web",
      "question_uk": "Товари доступні на сайті",
      "variations_en": [
        "web products",
        "online products",
        "e-commerce products"
      ],
      "variations_uk": [
        "веб товари",
        "онлайн товари",
        "товари для сайту"
      ],
      "sql": "SELECT COUNT(*) as WebProducts FROM dbo.Product WHERE Deleted = 0 AND IsForWeb = 1",
      "tables_used": [
        "Product"
      ]
    },
    {
      "id": "prod_with_images_015",
      "category": "filter",
      "complexity": "simple",
      "question_en": "Products with images",
      "question_uk": "Товари з зображеннями",
      "variations_en": [
        "products having images",
        "products with photos"
      ],
      "variations_uk": [
        "товари з фото",
        "товари із картинками"
      ],
      "sql": "SELECT COUNT(*) as ProductsWithImages FROM dbo.Product WHERE Deleted = 0 AND HasImage = 1",
      "tables_used": [
        "Product"
      ]
    },
    {
      "id": "prod_without_images_016",
      "category": "filter",
      "complexity": "simple",
      "question_en": "Products without images",
      "question_uk": "Товари без зображень",
      "variations_en": [
        "products missing images",
        "products with no photos"
      ],
      "variations_uk": [
        "товари без фото",
        "товари без картинок"
      ],
      "sql": "SELECT TOP 100 ID, Name, VendorCode FROM dbo.Product WHERE Deleted = 0 AND HasImage = 0 AND IsForWeb = 1 ORDER BY Created DESC",
      "tables_used": [
        "Product"
      ]
    },
    {
      "id": "prod_by_vendor_017",
      "category": "aggregation",
      "complexity": "medium",
      "question_en": "Count products by vendor code prefix",
      "question_uk": "Кількість товарів за префіксом коду",
      "variations_en": [
        "products grouped by brand",
        "vendor code distribution"
      ],
      "variations_uk": [
        "товари по брендах",
        "розподіл за кодами"
      ],
      "sql": "SELECT TOP 20 LEFT(VendorCode, 3) as CodePrefix, COUNT(*) as ProductCount FROM dbo.Product WHERE Deleted = 0 AND VendorCode IS NOT NULL AND LEN(VendorCode) >= 3 GROUP BY LEFT(VendorCode, 3) ORDER BY ProductCount DESC",
      "tables_used": [
        "Product"
      ]
    },
    {
      "id": "prod_sales_2024_018",
      "category": "filter",
      "complexity": "medium",
      "question_en": "Products sold in 2024",
      "question_uk": "Товари продані у 2024 році",
      "variations_en": [
        "2024 sales products",
        "what sold in 2024"
      ],
      "variations_uk": [
        "продажі 2024",
        "що продали у 2024"
      ],
      "sql": "SELECT DISTINCT TOP 100 p.ID, p.Name, p.VendorCode FROM dbo.Product p JOIN dbo.OrderItem oi ON p.ID = oi.ProductID WHERE p.Deleted = 0 AND oi.Deleted = 0 AND YEAR(oi.Created) = 2024 ORDER BY p.Name",
      "tables_used": [
        "Product",
        "OrderItem"
      ]
    },
    {
      "id": "prod_total_sold_019",
      "category": "aggregation",
      "complexity": "simple",
      "question_en": "Total quantity of all products sold",
      "question_uk": "Загальна кількість проданих товарів",
      "variations_en": [
        "total sales quantity",
        "how many items sold"
      ],
      "variations_uk": [
        "скільки всього продали",
        "загальний обсяг продажів"
      ],
      "sql": "SELECT SUM(Qty) as TotalQuantitySold FROM dbo.OrderItem WHERE Deleted = 0",
      "tables_used": [
        "OrderItem"
      ]
    },
    {
      "id": "prod_unique_sold_020",
      "category": "aggregation",
      "complexity": "simple",
      "question_en": "How many unique products were sold",
      "question_uk": "Скільки унікальних товарів продали",
      "variations_en": [
        "distinct products sold",
        "unique items sold"
      ],
      "variations_uk": [
        "різних товарів продано",
        "унікальні продажі"
      ],
      "sql": "SELECT COUNT(DISTINCT ProductID) as UniqueProductsSold FROM dbo.OrderItem WHERE Deleted = 0",
      "tables_used": [
        "OrderItem"
      ]
    },
    {
      "id": "prod_avg_qty_021",
      "category": "aggregation",
      "complexity": "medium",
      "question_en": "Average quantity per order item",
      "question_uk": "Середня кількість товару в позиції замовлення",
      "variations_en": [
        "average order quantity",
        "avg items per order line"
      ],
      "variations_uk": [
        "середня кількість",
        "середнє замовлення"
      ],
      "sql": "SELECT AVG(Qty) as AvgQuantity FROM dbo.OrderItem WHERE Deleted = 0 AND Qty > 0",
      "tables_used": [
        "OrderItem"
      ]
    },
    {
      "id": "prod_top_revenue_022",
      "category": "ranking",
      "complexity": "medium",
      "question_en": "Top 10 products by revenue",
      "question_uk": "Топ 10 товарів за виручкою",
      "variations_en": [
        "highest revenue products",
        "best products by money",
        "top earning products"
      ],
      "variations_uk": [
        "найприбутковіші товари",
        "товари з найбільшим доходом",
        "лідери по виручці"
      ],
      "sql": "SELECT TOP 10 p.ID, p.Name, p.VendorCode, SUM(oi.Qty * oi.PricePerItem) as TotalRevenue FROM dbo.Product p JOIN dbo.OrderItem oi ON p.ID = oi.ProductID WHERE p.Deleted = 0 AND oi.Deleted = 0 GROUP BY p.ID, p.Name, p.VendorCode ORDER BY TotalRevenue DESC",
      "tables_used": [
        "Product",
        "OrderItem"
      ]
    },
    {
      "id": "prod_has_analogues_023",
      "category": "filter",
      "complexity": "simple",
      "question_en": "Products with analogues",
      "question_uk": "Товари з аналогами",
      "variations_en": [
        "products having alternatives",
        "products with substitutes"
      ],
      "variations_uk": [
        "товари із замінниками",
        "є аналоги"
      ],
      "sql": "SELECT COUNT(*) as ProductsWithAnalogues FROM dbo.Product WHERE Deleted = 0 AND HasAnalogue = 1",
      "tables_used": [
        "Product"
      ]
    },
    {
      "id": "prod_list_all_024",
      "category": "listing",
      "complexity": "simple",
      "question_en": "List all products",
      "question_uk": "Покажи всі товари",
      "variations_en": [
        "show all products",
        "all products list",
        "display products"
      ],
      "variations_uk": [
        "список всіх товарів",
        "виведи товари",
        "всі продукти"
      ],
      "sql": "SELECT TOP 100 ID, Name, VendorCode, Created FROM dbo.Product WHERE Deleted = 0 ORDER BY Name",
      "tables_used": [
        "Product"
      ]
    },
    {
      "id": "prod_recent_sold_025",
      "category": "filter",
      "complexity": "medium",
      "question_en": "Recently sold products",
      "question_uk": "Нещодавно продані товари",
      "variations_en": [
        "latest sales",
        "products sold recently",
        "recent orders products"
      ],
      "variations_uk": [
        "останні продажі",
        "недавні продажі",
        "свіжі замовлення"
      ],
      "sql": "SELECT TOP 50 p.ID, p.Name, p.VendorCode, oi.Created as SoldDate, oi.Qty FROM dbo.Product p JOIN dbo.OrderItem oi ON p.ID = oi.ProductID WHERE p.Deleted = 0 AND oi.Deleted = 0 ORDER BY oi.Created DESC",
      "tables_used": [
        "Product",
        "OrderItem"
      ]
    },
    {
      "id": "product_sales_ranking_correct",
      "category": "ranking",
      "complexity": "medium",
      "question_en": "Top 10 products by sales quantity",
      "question_uk": "Топ 10 товарів за кількістю продажів",
      "variations_en": [
        "best sellers",
        "most sold products",
        "popular products"
      ],
      "variations_uk": [
        "найпопулярніші товари",
        "лідери продажів",
        "топ продаж"
      ],
      "sql": "SELECT TOP 10 p.Name, p.VendorCode, SUM(oi.Qty) as TotalSold FROM dbo.Product p JOIN dbo.OrderItem oi ON oi.ProductID = p.ID WHERE p.Deleted = 0 AND oi.Deleted = 0 GROUP BY p.ID, p.Name, p.VendorCode ORDER BY TotalSold DESC",
      "tables_used": [
        "Product",
        "OrderItem"
      ]
    },
    {
      "id": "product_by_code_search",
      "category": "search",
      "complexity": "simple",
      "question_en": "Find products by vendor code",
      "question_uk": "Знайти товар за артикулом",
      "variations_en": [
        "search by code",
        "product lookup by code"
      ],
      "variations_uk": [
        "пошук за кодом",
        "товар з кодом",
        "знайти за артикулом"
      ],
      "sql": "SELECT TOP 20 p.ID, p.Name, p.VendorCode, p.Description FROM dbo.Product p WHERE p.Deleted = 0 AND p.VendorCode LIKE N'%keyword%' ORDER BY p.VendorCode",
      "tables_used": [
        "Product"
      ]
    },
    {
      "id": "product_never_sold",
      "category": "filter",
      "complexity": "medium",
      "question_en": "Products never sold",
      "question_uk": "Товари без продажів",
      "variations_en": [
        "unsold products",
        "products with no sales"
      ],
      "variations_uk": [
        "непродані товари",
        "товари без замовлень"
      ],
      "sql": "SELECT p.ID, p.Name, p.VendorCode FROM dbo.Product p WHERE p.Deleted = 0 AND NOT EXISTS (SELECT 1 FROM dbo.OrderItem oi WHERE oi.ProductID = p.ID AND oi.Deleted = 0)",
      "tables_used": [
        "Product",
        "OrderItem"
      ]
    },
    {
      "id": "prod_search_aug_026",
      "category": "search",
      "complexity": "simple",
      "question_en": "Find products with AUG code",
      "question_uk": "Знайди товари з кодом AUG",
      "variations_en": [
        "AUG products",
        "show AUG items",
        "products with AUG",
        "list AUG products",
        "show all AUG products"
      ],
      "variations_uk": [
        "товари AUG",
        "покажи AUG",
        "продукти з AUG",
        "покажи всі товари AUG",
        "всі товари AUG",
        "список товарів AUG"
      ],
      "sql": "SELECT TOP 100 ID, Name, VendorCode FROM dbo.Product WHERE Deleted = 0 AND VendorCode LIKE N'AUG%' ORDER BY VendorCode",
      "tables_used": [
        "Product"
      ]
    },
    {
      "id": "prod_search_mg_027",
      "category": "search",
      "complexity": "simple",
      "question_en": "Find products with MG code",
      "question_uk": "Знайди товари з кодом MG",
      "variations_en": [
        "MG products",
        "show MG items",
        "products with MG",
        "list MG products",
        "show all MG products"
      ],
      "variations_uk": [
        "товари MG",
        "покажи MG",
        "продукти з MG",
        "покажи всі товари MG",
        "всі товари MG",
        "список товарів MG"
      ],
      "sql": "SELECT TOP 100 ID, Name, VendorCode FROM dbo.Product WHERE Deleted = 0 AND VendorCode LIKE N'MG%' ORDER BY VendorCode",
      "tables_used": [
        "Product"
      ]
    },
    {
      "id": "prod_search_fe_028",
      "category": "search",
      "complexity": "simple",
      "question_en": "Find products with FE code",
      "question_uk": "Знайди товари з кодом FE",
      "variations_en": [
        "FE products",
        "show FE items",
        "products with FE",
        "list FE products",
        "show all FE products"
      ],
      "variations_uk": [
        "товари FE",
        "покажи FE",
        "продукти з FE",
        "покажи всі товари FE",
        "всі товари FE",
        "список товарів FE"
      ],
      "sql": "SELECT TOP 100 ID, Name, VendorCode FROM dbo.Product WHERE Deleted = 0 AND VendorCode LIKE N'FE%' ORDER BY VendorCode",
      "tables_used": [
        "Product"
      ]
    },
    {
      "id": "prod_top_sales_aug_029",
      "category": "ranking",
      "complexity": "medium",
      "question_en": "Top selling AUG products",
      "question_uk": "Топ продажів AUG",
      "variations_en": [
        "best selling AUG",
        "AUG sales ranking",
        "most sold AUG products"
      ],
      "variations_uk": [
        "найкращі продажі AUG",
        "лідери продажів AUG",
        "топ AUG"
      ],
      "sql": "SELECT TOP 10 p.Name, p.VendorCode, SUM(oi.Qty) as TotalSold, COUNT(DISTINCT oi.OrderID) as OrderCount FROM dbo.Product p JOIN dbo.OrderItem oi ON oi.ProductID = p.ID WHERE p.Deleted = 0 AND oi.Deleted = 0 AND p.VendorCode LIKE N'AUG%' GROUP BY p.ID, p.Name, p.VendorCode ORDER BY TotalSold DESC",
      "tables_used": [
        "Product",
        "OrderItem"
      ]
    },
    {
      "id": "prod_top_sales_mg_030",
      "category": "ranking",
      "complexity": "medium",
      "question_en": "Top selling MG products",
      "question_uk": "Топ продажів MG",
      "variations_en": [
        "best selling MG",
        "MG sales ranking",
        "most sold MG products"
      ],
      "variations_uk": [
        "найкращі продажі MG",
        "лідери продажів MG",
        "топ MG"
      ],
      "sql": "SELECT TOP 10 p.Name, p.VendorCode, SUM(oi.Qty) as TotalSold, COUNT(DISTINCT oi.OrderID) as OrderCount FROM dbo.Product p JOIN dbo.OrderItem oi ON oi.ProductID = p.ID WHERE p.Deleted = 0 AND oi.Deleted = 0 AND p.VendorCode LIKE N'MG%' GROUP BY p.ID, p.Name, p.VendorCode ORDER BY TotalSold DESC",
      "tables_used": [
        "Product",
        "OrderItem"
      ]
    },
    {
      "id": "prod_top_sales_fe_031",
      "category": "ranking",
      "complexity": "medium",
      "question_en": "Top selling FE products",
      "question_uk": "Топ продажів FE",
      "variations_en": [
        "best selling FE",
        "FE sales ranking",
        "most sold FE products"
      ],
      "variations_uk": [
        "найкращі продажі FE",
        "лідери продажів FE",
        "топ FE"
      ],
      "sql": "SELECT TOP 10 p.Name, p.VendorCode, SUM(oi.Qty) as TotalSold, COUNT(DISTINCT oi.OrderID) as OrderCount FROM dbo.Product p JOIN dbo.OrderItem oi ON oi.ProductID = p.ID WHERE p.Deleted = 0 AND oi.Deleted = 0 AND p.VendorCode LIKE N'FE%' GROUP BY p.ID, p.Name, p.VendorCode ORDER BY TotalSold DESC",
      "tables_used": [
        "Product",
        "OrderItem"
      ]
    },
    {
      "id": "prod_count_by_brand_032",
      "category": "aggregation",
      "complexity": "simple",
      "question_en": "Count products by brand prefix",
      "question_uk": "Кількість товарів за брендом",
      "variations_en": [
        "how many products by brand",
        "product count per brand",
        "brand product statistics"
      ],
      "variations_uk": [
        "скільки товарів за брендом",
        "статистика по брендах",
        "товари за виробниками"
      ],
      "sql": "SELECT TOP 20 LEFT(VendorCode, 3) as Brand, COUNT(*) as ProductCount FROM dbo.Product WHERE Deleted = 0 AND VendorCode IS NOT NULL AND LEN(VendorCode) >= 3 GROUP BY LEFT(VendorCode, 3) ORDER BY ProductCount DESC",
      "tables_used": [
        "Product"
      ]
    }
  ]
}